tensorboard_plugin_profile/__init__.py
tensorboard_plugin_profile-2.21.4.dist-info/METADATA
tensorboard_plugin_profile-2.21.4.dist-info/WHEEL
tensorboard_plugin_profile-2.21.4.dist-info/top_level.txt
tensorboard_plugin_profile-2.21.4.dist-info/RECORD
