Metadata-Version: 2.4
Name: tensorboard_plugin_profile
Version: 2.21.4
Summary: XProf Profiler Plugin
Home-page: https://github.com/openxla/xprof
Author: Google Inc.
Author-email: packages@tensorflow.org
License: Apache 2.0
Keywords: jax pytorch xla tensorflow tensorboard xprof profile plugin
Classifier: Intended Audience :: Developers
Classifier: Intended Audience :: Education
Classifier: Intended Audience :: Science/Research
Classifier: License :: OSI Approved :: Apache Software License
Classifier: Programming Language :: Python :: 3
Classifier: Topic :: Scientific/Engineering :: Mathematics
Classifier: Topic :: Software Development :: Libraries :: Python Modules
Classifier: Topic :: Software Development :: Libraries
Requires-Python: >= 2.7, != 3.0.*, != 3.1.*
Requires-Dist: xprof==2.21.4
Dynamic: author
Dynamic: author-email
Dynamic: classifier
Dynamic: description
Dynamic: description-content-type
Dynamic: home-page
Dynamic: keywords
Dynamic: license
Dynamic: requires-dist
Dynamic: requires-python
Dynamic: summary
